mastercurves/__init__.py
mastercurves/mc.py
mastercurves/transforms/__init__.py
mastercurves/transforms/multiply.py
mastercurves/transforms/powerlawage.py
mastercurves-0.1.1.dist-info/LICENSE
mastercurves-0.1.1.dist-info/METADATA
mastercurves-0.1.1.dist-info/WHEEL
mastercurves-0.1.1.dist-info/top_level.txt
mastercurves-0.1.1.dist-info/RECORD
