Metadata-Version: 2.1
Name: mastercurves
Version: 0.1.1
Summary: Python package for building master curves from data
Home-page: UNKNOWN
Author: Kyle Lennon
Author-email: <kyle.lennon08@gmail.com>
License: GNU GPLv3
Keywords: python,master,curves,mastercurves,Bayesian,Gaussian,process,regression,machine,learning,statistics
Platform: UNKNOWN
Classifier: Development Status :: 3 - Alpha
Classifier: Intended Audience :: End Users/Desktop
Classifier: Programming Language :: Python :: 3
Classifier: Operating System :: MacOS :: MacOS X
Classifier: Operating System :: Microsoft :: Windows
Requires-Dist: numpy
Requires-Dist: matplotlib
Requires-Dist: scikit-learn
Requires-Dist: scipy
Requires-Dist: pandas
Requires-Dist: numdifftools
